better_result/__init__.py
better_result/_result.py
better_result/py.typed
better_result-0.1.0.dist-info/LICENSE
better_result-0.1.0.dist-info/METADATA
better_result-0.1.0.dist-info/WHEEL
better_result-0.1.0.dist-info/top_level.txt
better_result-0.1.0.dist-info/RECORD
